{
  "2026-07-13": [
    {
      "start": "10:30",
      "end": "13:30",
      "avail": 198
    },
    {
      "start": "14:30",
      "end": "17:30",
      "avail": 94
    }
  ],
  "2026-07-14": [
    {
      "start": "10:30",
      "end": "13:30",
      "avail": 502
    },
    {
      "start": "14:30",
      "end": "17:30",
      "avail": 382
    }
  ],
  "2026-07-15": [
    {
      "start": "10:30",
      "end": "13:30",
      "avail": 614
    },
    {
      "start": "14:30",
      "end": "17:30",
      "avail": 522
    },
    {
      "start": "18:00",
      "end": "20:30",
      "avail": 83
    }
  ],
  "2026-07-16": [
    {
      "start": "10:30",
      "end": "13:30",
      "avail": 800
    },
    {
      "start": "14:30",
      "end": "17:30",
      "avail": 800
    },
    {
      "start": "18:00",
      "end": "20:30",
      "avail": 300
    }
  ],
  "2026-07-17": [
    {
      "start": "10:30",
      "end": "13:30",
      "avail": 800
    },
    {
      "start": "14:30",
      "end": "17:30",
      "avail": 800
    },
    {
      "start": "18:00",
      "end": "20:30",
      "avail": 300
    }
  ]
}
